README.rst
setup.cfg
setup.py
redash_client/__init__.py
redash_client/client.py
redash_client/constants.py
redash_client.egg-info/PKG-INFO
redash_client.egg-info/SOURCES.txt
redash_client.egg-info/dependency_links.txt
redash_client.egg-info/requires.txt
redash_client.egg-info/top_level.txt