Metadata-Version: 1.0
Name: redash-client
Version: 0.2.2
Summary: A client for the re:dash API for stmo (https://sql.telemetry.mozilla.org)
Home-page: https://github.com/mozilla/redash_client
Author: Marina Samuel
Author-email: msamuel@mozilla.com
License: UNKNOWN
Keywords: redash,experiments,a/b tests
Platform: UNKNOWN
